{
"meta":{"test_sets":["test"],"test_metrics":[{"best_value":"Min","name":"MultiClass"}],"learn_metrics":[{"best_value":"Min","name":"MultiClass"}],"launch_mode":"Train","parameters":"","iteration_count":200,"learn_sets":["learn"],"name":"experiment"},
"iterations":[
{"learn":[2.413392574],"iteration":0,"passed_time":0.05923823908,"remaining_time":11.78840958,"test":[2.403225837]},
{"learn":[2.144523538],"iteration":1,"passed_time":0.1273942292,"remaining_time":12.61202869,"test":[2.135705532]},
{"learn":[1.965712965],"iteration":2,"passed_time":0.2150778509,"remaining_time":14.12344554,"test":[1.953323627]},
{"learn":[1.85381203],"iteration":3,"passed_time":0.2810221107,"remaining_time":13.77008343,"test":[1.829997248]},
{"learn":[1.638607654],"iteration":4,"passed_time":0.3404805896,"remaining_time":13.27874299,"test":[1.607178188]},
{"learn":[1.496291659],"iteration":5,"passed_time":0.392659616,"remaining_time":12.69599425,"test":[1.465263541]},
{"learn":[1.399629891],"iteration":6,"passed_time":0.4459945885,"remaining_time":12.29670794,"test":[1.3710419]},
{"learn":[1.318069386],"iteration":7,"passed_time":0.4961267104,"remaining_time":11.90704105,"test":[1.290290828]},
{"learn":[1.263346389],"iteration":8,"passed_time":0.550940739,"remaining_time":11.69218679,"test":[1.23922209]},
{"learn":[1.220584789],"iteration":9,"passed_time":0.6042547542,"remaining_time":11.48084033,"test":[1.200826635]},
{"learn":[1.183333525],"iteration":10,"passed_time":0.6550552198,"remaining_time":11.25503969,"test":[1.169086552]},
{"learn":[1.154480674],"iteration":11,"passed_time":0.7062528337,"remaining_time":11.06462773,"test":[1.141053318]},
{"learn":[1.133084626],"iteration":12,"passed_time":0.7618140358,"remaining_time":10.9584019,"test":[1.122418529]},
{"learn":[1.111330816],"iteration":13,"passed_time":0.8223215491,"remaining_time":10.92512915,"test":[1.101686658]},
{"learn":[1.091080388],"iteration":14,"passed_time":0.8807528257,"remaining_time":10.86261818,"test":[1.087189201]},
{"learn":[1.074093336],"iteration":15,"passed_time":0.9385621731,"remaining_time":10.79346499,"test":[1.073818543]},
{"learn":[1.059786248],"iteration":16,"passed_time":0.9951709097,"remaining_time":10.71272215,"test":[1.06269663]},
{"learn":[1.046273854],"iteration":17,"passed_time":1.04551373,"remaining_time":10.57130549,"test":[1.055224273]},
{"learn":[1.03484334],"iteration":18,"passed_time":1.108457546,"remaining_time":10.55951663,"test":[1.04569937]},
{"learn":[1.024746284],"iteration":19,"passed_time":1.164335734,"remaining_time":10.4790216,"test":[1.040426657]},
{"learn":[1.018470761],"iteration":20,"passed_time":1.244329131,"remaining_time":10.60642449,"test":[1.035745807]},
{"learn":[1.011967547],"iteration":21,"passed_time":1.322149712,"remaining_time":10.69739312,"test":[1.030795566]},
{"learn":[1.00295956],"iteration":22,"passed_time":1.391550936,"remaining_time":10.70889198,"test":[1.025102729]},
{"learn":[0.993415368],"iteration":23,"passed_time":1.468923955,"remaining_time":10.772109,"test":[1.020735704]},
{"learn":[0.9853552429],"iteration":24,"passed_time":1.525955213,"remaining_time":10.68168649,"test":[1.017322067]},
{"learn":[0.9773270474],"iteration":25,"passed_time":1.587833163,"remaining_time":10.62626809,"test":[1.011675926]},
{"learn":[0.9716330593],"iteration":26,"passed_time":1.667545072,"remaining_time":10.68464065,"test":[1.008704001]},
{"learn":[0.9678531004],"iteration":27,"passed_time":1.730724128,"remaining_time":10.63159107,"test":[1.006108277]},
{"learn":[0.9651633081],"iteration":28,"passed_time":1.909133313,"remaining_time":11.25730333,"test":[1.004571018]},
{"learn":[0.9491453756],"iteration":29,"passed_time":1.969098726,"remaining_time":11.15822612,"test":[0.9942119012]},
{"learn":[0.943480146],"iteration":30,"passed_time":2.039273539,"remaining_time":11.11732994,"test":[0.9920634123]},
{"learn":[0.9395074632],"iteration":31,"passed_time":2.114531365,"remaining_time":11.10128966,"test":[0.9889809631]},
{"learn":[0.9354677764],"iteration":32,"passed_time":2.192394819,"remaining_time":11.09484651,"test":[0.9870750703]},
{"learn":[0.9335704058],"iteration":33,"passed_time":2.265497495,"remaining_time":11.06095836,"test":[0.9859355792]},
{"learn":[0.9302199523],"iteration":34,"passed_time":2.328987161,"remaining_time":10.9795109,"test":[0.9839564587]},
{"learn":[0.926212304],"iteration":35,"passed_time":2.392530283,"remaining_time":10.89930462,"test":[0.9814341382]},
{"learn":[0.9236879573],"iteration":36,"passed_time":2.459106347,"remaining_time":10.83336039,"test":[0.9802450945]},
{"learn":[0.9201692038],"iteration":37,"passed_time":2.540609798,"remaining_time":10.83102072,"test":[0.9781643576]},
{"learn":[0.9181723828],"iteration":38,"passed_time":2.601949148,"remaining_time":10.74137981,"test":[0.9766743765]},
{"learn":[0.9156563132],"iteration":39,"passed_time":2.668332762,"remaining_time":10.67333105,"test":[0.9760344048]},
{"learn":[0.9126714675],"iteration":40,"passed_time":2.740146373,"remaining_time":10.6264213,"test":[0.9758553368]},
{"learn":[0.9100923892],"iteration":41,"passed_time":2.819734039,"remaining_time":10.60757091,"test":[0.975494158]},
{"learn":[0.8987807379],"iteration":42,"passed_time":2.889708069,"remaining_time":10.55079458,"test":[0.9683548478]},
{"learn":[0.897550862],"iteration":43,"passed_time":2.963036152,"remaining_time":10.50530999,"test":[0.9676133865]},
{"learn":[0.8956424767],"iteration":44,"passed_time":3.064252059,"remaining_time":10.55464598,"test":[0.9662659959]},
{"learn":[0.8926598692],"iteration":45,"passed_time":3.124920398,"remaining_time":10.46169003,"test":[0.9655929752]},
{"learn":[0.8899817613],"iteration":46,"passed_time":3.205845002,"remaining_time":10.43604862,"test":[0.9652221523]},
{"learn":[0.8870153735],"iteration":47,"passed_time":3.26699561,"remaining_time":10.3454861,"test":[0.9653692789]},
{"learn":[0.8776272623],"iteration":48,"passed_time":3.336437665,"remaining_time":10.28167525,"test":[0.9561217305]},
{"learn":[0.8695710878],"iteration":49,"passed_time":3.4063187,"remaining_time":10.2189561,"test":[0.9511972199]},
{"learn":[0.8678141942],"iteration":50,"passed_time":3.512661285,"remaining_time":10.26248101,"test":[0.9502695613]},
{"learn":[0.8627357567],"iteration":51,"passed_time":3.585350606,"remaining_time":10.20445942,"test":[0.9475828584]},
{"learn":[0.8585433191],"iteration":52,"passed_time":3.660325861,"remaining_time":10.15222456,"test":[0.9471282299]},
{"learn":[0.84907136],"iteration":53,"passed_time":3.732448083,"remaining_time":10.09143371,"test":[0.939237186]},
{"learn":[0.845671603],"iteration":54,"passed_time":3.808135889,"remaining_time":10.03963098,"test":[0.9373458465]},
{"learn":[0.839988004],"iteration":55,"passed_time":3.886557276,"remaining_time":9.994004424,"test":[0.9340191365]},
{"learn":[0.8360865189],"iteration":56,"passed_time":3.963812592,"remaining_time":9.944301766,"test":[0.9329409917]},
{"learn":[0.8322976901],"iteration":57,"passed_time":4.025786328,"remaining_time":9.856235494,"test":[0.9328178781]},
{"learn":[0.8263270939],"iteration":58,"passed_time":4.094944689,"remaining_time":9.786223747,"test":[0.9287637299]},
{"learn":[0.8234070812],"iteration":59,"passed_time":4.164811766,"remaining_time":9.71789412,"test":[0.9271097492]},
{"learn":[0.8183723267],"iteration":60,"passed_time":4.249745724,"remaining_time":9.683846813,"test":[0.9249487311]},
{"learn":[0.8059254647],"iteration":61,"passed_time":4.320020698,"remaining_time":9.615529942,"test":[0.9147075128]},
{"learn":[0.8046464957],"iteration":62,"passed_time":4.398250052,"remaining_time":9.564448527,"test":[0.9145450213]},
{"learn":[0.8007816129],"iteration":63,"passed_time":4.487895624,"remaining_time":9.536778202,"test":[0.912074299]},
{"learn":[0.7977787708],"iteration":64,"passed_time":4.564571676,"remaining_time":9.480264249,"test":[0.9113378614]},
{"learn":[0.7967134103],"iteration":65,"passed_time":4.651869524,"remaining_time":9.44470479,"test":[0.9105630298]},
{"learn":[0.7940769554],"iteration":66,"passed_time":4.727288425,"remaining_time":9.384020307,"test":[0.9091321863]},
{"learn":[0.7892173886],"iteration":67,"passed_time":4.800999156,"remaining_time":9.319586598,"test":[0.9054729859]},
{"learn":[0.7823120368],"iteration":68,"passed_time":4.868046073,"remaining_time":9.2422324,"test":[0.8974049829]},
{"learn":[0.7811397619],"iteration":69,"passed_time":4.930834564,"remaining_time":9.157264189,"test":[0.8968429294]},
{"learn":[0.7762081717],"iteration":70,"passed_time":5.001007626,"remaining_time":9.0863378,"test":[0.8930122363]},
{"learn":[0.7742787122],"iteration":71,"passed_time":5.077393566,"remaining_time":9.026477451,"test":[0.8932505663]},
{"learn":[0.7720912066],"iteration":72,"passed_time":5.141078306,"remaining_time":8.944067738,"test":[0.8920158717]},
{"learn":[0.7675548936],"iteration":73,"passed_time":5.216314841,"remaining_time":8.881833379,"test":[0.8875362322]},
{"learn":[0.7658470098],"iteration":74,"passed_time":5.286460156,"remaining_time":8.810766926,"test":[0.8874325094]},
{"learn":[0.7611974219],"iteration":75,"passed_time":5.357038824,"remaining_time":8.740431766,"test":[0.884386216]},
{"learn":[0.7590949807],"iteration":76,"passed_time":5.420183923,"remaining_time":8.658215877,"test":[0.8842160616]},
{"learn":[0.7532672098],"iteration":77,"passed_time":5.491090785,"remaining_time":8.588629177,"test":[0.8798804371]},
{"learn":[0.7519368192],"iteration":78,"passed_time":5.567474808,"remaining_time":8.527398124,"test":[0.8798159785]},
{"learn":[0.7458695607],"iteration":79,"passed_time":5.636808744,"remaining_time":8.455213115,"test":[0.8747525535]},
{"learn":[0.743338842],"iteration":80,"passed_time":5.715003474,"remaining_time":8.396116215,"test":[0.8740360135]},
{"learn":[0.7416397158],"iteration":81,"passed_time":5.78996798,"remaining_time":8.331905142,"test":[0.8717794108]},
{"learn":[0.7398265854],"iteration":82,"passed_time":5.85054524,"remaining_time":8.247154134,"test":[0.8719535681]},
{"learn":[0.7324516174],"iteration":83,"passed_time":5.922619298,"remaining_time":8.178855221,"test":[0.86294349]},
{"learn":[0.728264687],"iteration":84,"passed_time":5.994184921,"remaining_time":8.109779599,"test":[0.8597751323]},
{"learn":[0.726892184],"iteration":85,"passed_time":6.055936709,"remaining_time":8.027637033,"test":[0.8599449175]},
{"learn":[0.7229445891],"iteration":86,"passed_time":6.117755828,"remaining_time":7.946050673,"test":[0.8593028989]},
{"learn":[0.7184368905],"iteration":87,"passed_time":6.188483657,"remaining_time":7.876251927,"test":[0.8558972588]},
{"learn":[0.7168711614],"iteration":88,"passed_time":6.257704514,"remaining_time":7.804552821,"test":[0.8562089284]},
{"learn":[0.7159403732],"iteration":89,"passed_time":6.325979123,"remaining_time":7.731752262,"test":[0.8562585196]},
{"learn":[0.7055494895],"iteration":90,"passed_time":6.399646023,"remaining_time":7.665510072,"test":[0.8469196268]},
{"learn":[0.703505827],"iteration":91,"passed_time":6.48753951,"remaining_time":7.615807251,"test":[0.8472856597]},
{"learn":[0.7005092496],"iteration":92,"passed_time":6.560036048,"remaining_time":7.547568356,"test":[0.8459501079]},
{"learn":[0.698164004],"iteration":93,"passed_time":6.632173311,"remaining_time":7.478833734,"test":[0.8445271662]},
{"learn":[0.6935667455],"iteration":94,"passed_time":6.697528098,"remaining_time":7.402531056,"test":[0.8413512351]},
{"learn":[0.6896484574],"iteration":95,"passed_time":6.762961299,"remaining_time":7.326541407,"test":[0.8392620937]},
{"learn":[0.6884042793],"iteration":96,"passed_time":6.825884366,"remaining_time":7.248104017,"test":[0.8393858168]},
{"learn":[0.6817237028],"iteration":97,"passed_time":6.890199827,"remaining_time":7.171432473,"test":[0.8342465661]},
{"learn":[0.6792424071],"iteration":98,"passed_time":6.96546961,"remaining_time":7.106186168,"test":[0.8336960528]},
{"learn":[0.674399574],"iteration":99,"passed_time":7.038651325,"remaining_time":7.038651325,"test":[0.8295786701]},
{"learn":[0.6717703982],"iteration":100,"passed_time":7.118983247,"remaining_time":6.978013282,"test":[0.8271637112]},
{"learn":[0.6708445184],"iteration":101,"passed_time":7.183639609,"remaining_time":6.901928252,"test":[0.8274442246]},
{"learn":[0.6698745144],"iteration":102,"passed_time":7.24858254,"remaining_time":6.826335014,"test":[0.8269064408]},
{"learn":[0.6677581666],"iteration":103,"passed_time":7.314102945,"remaining_time":6.751479641,"test":[0.826712362]},
{"learn":[0.6668933468],"iteration":104,"passed_time":7.384211927,"remaining_time":6.680953649,"test":[0.8266723027]},
{"learn":[0.6650724289],"iteration":105,"passed_time":7.44073471,"remaining_time":6.598387384,"test":[0.8266089256]},
{"learn":[0.6640191086],"iteration":106,"passed_time":7.50652106,"remaining_time":6.524359426,"test":[0.8268790661]},
{"learn":[0.6610143727],"iteration":107,"passed_time":7.579814186,"remaining_time":6.456878751,"test":[0.8254494503]},
{"learn":[0.6603375653],"iteration":108,"passed_time":7.658732466,"remaining_time":6.393987655,"test":[0.8249848125]},
{"learn":[0.656850328],"iteration":109,"passed_time":7.72387943,"remaining_time":6.319537715,"test":[0.821423902]},
{"learn":[0.6557572033],"iteration":110,"passed_time":7.806399584,"remaining_time":6.259185252,"test":[0.8217470744]},
{"learn":[0.6540036685],"iteration":111,"passed_time":7.887629881,"remaining_time":6.197423478,"test":[0.8223060742]},
{"learn":[0.6517911295],"iteration":112,"passed_time":7.960957589,"remaining_time":6.129232834,"test":[0.8211268232]},
{"learn":[0.6512274713],"iteration":113,"passed_time":8.027103922,"remaining_time":6.055534538,"test":[0.8208212394]},
{"learn":[0.6476631353],"iteration":114,"passed_time":8.089840332,"remaining_time":5.979447202,"test":[0.8163538145]},
{"learn":[0.6430825581],"iteration":115,"passed_time":8.162261206,"remaining_time":5.910602943,"test":[0.8124760283]},
{"learn":[0.6413262574],"iteration":116,"passed_time":8.229368204,"remaining_time":5.837927871,"test":[0.8121539513]},
{"learn":[0.6395917453],"iteration":117,"passed_time":8.300230151,"remaining_time":5.767956546,"test":[0.8103827403]},
{"learn":[0.6381377533],"iteration":118,"passed_time":8.387414629,"remaining_time":5.709080546,"test":[0.8108342163]},
{"learn":[0.6380972167],"iteration":119,"passed_time":8.42774475,"remaining_time":5.6184965,"test":[0.8107353243]},
{"learn":[0.6370229665],"iteration":120,"passed_time":8.506118514,"remaining_time":5.553581509,"test":[0.8104709097]},
{"learn":[0.6356532465],"iteration":121,"passed_time":8.565306672,"remaining_time":5.476179675,"test":[0.8107364703]},
{"learn":[0.634549408],"iteration":122,"passed_time":8.646817789,"remaining_time":5.413048535,"test":[0.8119740002]},
{"learn":[0.6313262111],"iteration":123,"passed_time":8.733436877,"remaining_time":5.352751634,"test":[0.8084081475]},
{"learn":[0.6306978447],"iteration":124,"passed_time":8.794138465,"remaining_time":5.276483079,"test":[0.808038605]},
{"learn":[0.6271869385],"iteration":125,"passed_time":8.865739878,"remaining_time":5.206863103,"test":[0.8038052459]},
{"learn":[0.6229645095],"iteration":126,"passed_time":8.936793024,"remaining_time":5.136896778,"test":[0.8023255406]},
{"learn":[0.6219759284],"iteration":127,"passed_time":9.011823986,"remaining_time":5.069150992,"test":[0.8025736664]},
{"learn":[0.6213026814],"iteration":128,"passed_time":9.077316517,"remaining_time":4.996042424,"test":[0.802854672]},
{"learn":[0.6197244327],"iteration":129,"passed_time":9.154012317,"remaining_time":4.929083555,"test":[0.8022105141]},
{"learn":[0.6176604459],"iteration":130,"passed_time":9.228974115,"remaining_time":4.861062702,"test":[0.802285611]},
{"learn":[0.6162229666],"iteration":131,"passed_time":9.294267572,"remaining_time":4.787956022,"test":[0.8023296368]},
{"learn":[0.6133406229],"iteration":132,"passed_time":9.367281711,"remaining_time":4.7188562,"test":[0.7996318579]},
{"learn":[0.6112035299],"iteration":133,"passed_time":9.438289026,"remaining_time":4.64870952,"test":[0.7979375183]},
{"learn":[0.6101715589],"iteration":134,"passed_time":9.54037006,"remaining_time":4.59351151,"test":[0.7976827762]},
{"learn":[0.6084071477],"iteration":135,"passed_time":9.640120994,"remaining_time":4.536527527,"test":[0.7955584423]},
{"learn":[0.6045102739],"iteration":136,"passed_time":9.710711829,"remaining_time":4.465509819,"test":[0.7920605521]},
{"learn":[0.6002212213],"iteration":137,"passed_time":9.775290736,"remaining_time":4.391797287,"test":[0.7904165149]},
{"learn":[0.5976295889],"iteration":138,"passed_time":9.84682761,"remaining_time":4.321269671,"test":[0.7879333256]},
{"learn":[0.597191573],"iteration":139,"passed_time":9.9167776,"remaining_time":4.250047543,"test":[0.7882417852]},
{"learn":[0.5943430001],"iteration":140,"passed_time":10.08801362,"remaining_time":4.221225557,"test":[0.7863466415]},
{"learn":[0.5906007389],"iteration":141,"passed_time":10.17491982,"remaining_time":4.155953166,"test":[0.783159134]},
{"learn":[0.5878280368],"iteration":142,"passed_time":10.25099215,"remaining_time":4.086059807,"test":[0.7805884806]},
{"learn":[0.5872390168],"iteration":143,"passed_time":10.32204821,"remaining_time":4.01412986,"test":[0.781168645]},
{"learn":[0.5869724993],"iteration":144,"passed_time":10.39574011,"remaining_time":3.943211766,"test":[0.780994106]},
{"learn":[0.5830695335],"iteration":145,"passed_time":10.46593746,"remaining_time":3.870963172,"test":[0.7785353245]},
{"learn":[0.5828908895],"iteration":146,"passed_time":10.55633079,"remaining_time":3.806024027,"test":[0.7784329937]},
{"learn":[0.5821730455],"iteration":147,"passed_time":10.63810511,"remaining_time":3.737712605,"test":[0.7782156184]},
{"learn":[0.5793833641],"iteration":148,"passed_time":10.71283571,"remaining_time":3.666809537,"test":[0.7759080757]},
{"learn":[0.5763545054],"iteration":149,"passed_time":10.87727142,"remaining_time":3.625757139,"test":[0.7742517335]},
{"learn":[0.5746130608],"iteration":150,"passed_time":10.95786599,"remaining_time":3.5558638,"test":[0.772754116]},
{"learn":[0.5740444615],"iteration":151,"passed_time":11.02730255,"remaining_time":3.482306069,"test":[0.772712312]},
{"learn":[0.5734786063],"iteration":152,"passed_time":11.0948057,"remaining_time":3.408208286,"test":[0.7726773719]},
{"learn":[0.5723507931],"iteration":153,"passed_time":11.16488955,"remaining_time":3.33496701,"test":[0.7730553773]},
{"learn":[0.5701316037],"iteration":154,"passed_time":11.23946854,"remaining_time":3.263071511,"test":[0.7714802901]},
{"learn":[0.5690458316],"iteration":155,"passed_time":11.31869772,"remaining_time":3.192453203,"test":[0.7713387476]},
{"learn":[0.5672214716],"iteration":156,"passed_time":11.39975507,"remaining_time":3.12222591,"test":[0.7705117355]},
{"learn":[0.5635613361],"iteration":157,"passed_time":11.46666649,"remaining_time":3.048101219,"test":[0.7678319483]},
{"learn":[0.5628430048],"iteration":158,"passed_time":11.5321921,"remaining_time":2.973709913,"test":[0.7682577183]},
{"learn":[0.56114521],"iteration":159,"passed_time":11.61144974,"remaining_time":2.902862435,"test":[0.7677987472]},
{"learn":[0.5601067688],"iteration":160,"passed_time":11.68724871,"remaining_time":2.831072669,"test":[0.7684375378]},
{"learn":[0.5595163685],"iteration":161,"passed_time":11.76718977,"remaining_time":2.760205009,"test":[0.7679952513]},
{"learn":[0.559067987],"iteration":162,"passed_time":11.85851531,"remaining_time":2.691810224,"test":[0.7684840862]},
{"learn":[0.5584511652],"iteration":163,"passed_time":11.93534477,"remaining_time":2.61995373,"test":[0.7685661884]},
{"learn":[0.5578036037],"iteration":164,"passed_time":12.00659841,"remaining_time":2.546854208,"test":[0.768232812]},
{"learn":[0.5575706545],"iteration":165,"passed_time":12.0781907,"remaining_time":2.473846287,"test":[0.7681883343]},
{"learn":[0.5562933208],"iteration":166,"passed_time":12.15285522,"remaining_time":2.401462408,"test":[0.7680263453]},
{"learn":[0.5556209716],"iteration":167,"passed_time":12.22869072,"remaining_time":2.329274424,"test":[0.7681117874]},
{"learn":[0.5522616727],"iteration":168,"passed_time":12.31062778,"remaining_time":2.258162492,"test":[0.7674583753]},
{"learn":[0.551611723],"iteration":169,"passed_time":12.37440902,"remaining_time":2.183719238,"test":[0.7673650422]},
{"learn":[0.5509394699],"iteration":170,"passed_time":12.44505639,"remaining_time":2.110565119,"test":[0.768079683]},
{"learn":[0.5502944525],"iteration":171,"passed_time":12.51828019,"remaining_time":2.037859565,"test":[0.7679321363]},
{"learn":[0.5483907122],"iteration":172,"passed_time":12.59375042,"remaining_time":1.96549862,"test":[0.7666139403]},
{"learn":[0.5470138232],"iteration":173,"passed_time":12.66176487,"remaining_time":1.891987855,"test":[0.766656878]},
{"learn":[0.5461828056],"iteration":174,"passed_time":12.73243083,"remaining_time":1.81891869,"test":[0.7666730779]},
{"learn":[0.5448928978],"iteration":175,"passed_time":12.79818818,"remaining_time":1.745207479,"test":[0.7661768328]},
{"learn":[0.5441092833],"iteration":176,"passed_time":12.86203616,"remaining_time":1.671338033,"test":[0.7665539287]},
{"learn":[0.5435435135],"iteration":177,"passed_time":12.93232872,"remaining_time":1.598377707,"test":[0.7667979023]},
{"learn":[0.5429583867],"iteration":178,"passed_time":13.01851608,"remaining_time":1.527311942,"test":[0.7663050456]},
{"learn":[0.5416133489],"iteration":179,"passed_time":13.09130631,"remaining_time":1.45458959,"test":[0.7660776262]},
{"learn":[0.5402839647],"iteration":180,"passed_time":13.16548252,"remaining_time":1.382011977,"test":[0.7669166295]},
{"learn":[0.5398377652],"iteration":181,"passed_time":13.25075126,"remaining_time":1.31051386,"test":[0.7670694044]},
{"learn":[0.5391926802],"iteration":182,"passed_time":13.32246025,"remaining_time":1.237605597,"test":[0.7670866097]},
{"learn":[0.5386666609],"iteration":183,"passed_time":13.40476529,"remaining_time":1.165631764,"test":[0.7672012653]},
{"learn":[0.5369426767],"iteration":184,"passed_time":13.4884498,"remaining_time":1.093658092,"test":[0.7663311462]},
{"learn":[0.5364282649],"iteration":185,"passed_time":13.56964177,"remaining_time":1.021370886,"test":[0.766268401]},
{"learn":[0.5358223903],"iteration":186,"passed_time":13.64252266,"remaining_time":0.9484106664,"test":[0.7663140839]},
{"learn":[0.5343392992],"iteration":187,"passed_time":13.69987882,"remaining_time":0.8744603504,"test":[0.7663649431]},
{"learn":[0.533907192],"iteration":188,"passed_time":13.78215599,"remaining_time":0.8021360628,"test":[0.7664290757]},
{"learn":[0.5290112625],"iteration":189,"passed_time":13.844565,"remaining_time":0.7286613156,"test":[0.7613557389]},
{"learn":[0.5267657258],"iteration":190,"passed_time":13.93273789,"remaining_time":0.6565164449,"test":[0.7587903905]},
{"learn":[0.5248601945],"iteration":191,"passed_time":14.00160343,"remaining_time":0.5834001428,"test":[0.7574709646]},
{"learn":[0.5196289664],"iteration":192,"passed_time":14.0730681,"remaining_time":0.5104221589,"test":[0.7515168581]},
{"learn":[0.5185933168],"iteration":193,"passed_time":14.13887636,"remaining_time":0.437284836,"test":[0.7518539582]},
{"learn":[0.517202275],"iteration":194,"passed_time":14.19611244,"remaining_time":0.3640028832,"test":[0.7518389377]},
{"learn":[0.516793347],"iteration":195,"passed_time":14.26898097,"remaining_time":0.2912036932,"test":[0.7519859237]},
{"learn":[0.5160092366],"iteration":196,"passed_time":14.34191419,"remaining_time":0.2184047846,"test":[0.7518727225]},
{"learn":[0.5138218516],"iteration":197,"passed_time":14.41271568,"remaining_time":0.1455829867,"test":[0.7496697569]},
{"learn":[0.5133090285],"iteration":198,"passed_time":14.49605988,"remaining_time":0.07284452202,"test":[0.7500446061]},
{"learn":[0.5125797882],"iteration":199,"passed_time":14.56459998,"remaining_time":0,"test":[0.750594473]}
]}